{"resourceType":"ValueSet","id":"case-status","text":{"status":"generated","div":"<div xmlns=\"http://www.w3.org/1999/xhtml\"><h2>Case Status Codes</h2><div><p>Codes identifying the stage lifecycle stage of the case.</p>\n</div><p>This value set includes codes from the following code systems:</p><ul><li>Include all codes defined in <a href=\"CodeSystem-case-status.html\"><code>http://fhir.hl7.org/us/ecr/CodeSystem/case-status</code></a></li></ul></div>"},"url":"http://fhir.hl7.org/us/ecr/ValueSet/case-status","version":"0.0.0","name":"Case Status Codes","status":"draft","experimental":false,"date":"2017-09-20T10:45:12-07:00","publisher":"{ site.data.fhir.ig.publisher }","contact":[{"name":"HL7 Public Health and Emergency Response WorkGroup","telecom":[{"system":"url","value":"http://www.hl7.org/Special/committees/pher/index.cfm"}]}],"description":"Codes identifying the stage lifecycle stage of the case.","jurisdiction":[{"coding":[{"system":"urn:iso:std:iso:3166","code":"US","display":"United States Minor Outlying Islands (the)"}]}],"compose":{"include":[{"system":"http://fhir.hl7.org/us/ecr/CodeSystem/case-status"}]},"expansion":{"identifier":"urn:uuid:b6e41216-77fd-4fc9-8bac-1c20962da361","timestamp":"2017-11-27T00:15:28-08:00","total":7,"parameter":[{"name":"profile","valueUri":"http://hl7.org/fhir/ExpansionProfile/dc8fd4bc-091a-424a-8a3b-6198ef146891"},{"name":"version","valueUri":"http://fhir.hl7.org/us/ecr/CodeSystem/case-status|0.0.0"}],"contains":[{"system":"http://fhir.hl7.org/us/ecr/CodeSystem/case-status","code":"in-progress","display":"In Progress"},{"system":"http://fhir.hl7.org/us/ecr/CodeSystem/case-status","code":"suspended","display":"Suspended"},{"system":"http://fhir.hl7.org/us/ecr/CodeSystem/case-status","code":"aborted","display":"Aborted"},{"system":"http://fhir.hl7.org/us/ecr/CodeSystem/case-status","code":"completed","display":"Completed"},{"system":"http://fhir.hl7.org/us/ecr/CodeSystem/case-status","code":"reopened","display":"Reopened"},{"system":"http://fhir.hl7.org/us/ecr/CodeSystem/case-status","code":"entered-in-error","display":"Entered in Error"},{"system":"http://fhir.hl7.org/us/ecr/CodeSystem/case-status","code":"unknown","display":"Unknown"}]}}