<?xml version="1.0" encoding="UTF-8"?>
<Library
    xmlns="http://hl7.org/fhir">
    <id value="library-rctc"/>
    <meta>
        <versionId value="2"/>
        <lastUpdated value="2019-09-14T19:55:20.000-04:00"/>
        <profile value="http://hl7.org/fhir/us/ecr/StructureDefinition/ersd-valueset-library"/>
    </meta>
    <url value="http://hl7.org/fhir/us/ecr/Library/library-rctc"/>
    <status value="active"/>
    <type>
        <coding>
            <system value="http://terminology.hl7.org/CodeSystem/library-type"/>
            <code value="asset-collection"/>
        </coding>
    </type>
    <relatedArtifact>
        <type value="composed-of"/>
        <resource value="http://hl7.org/fhir/us/ecr/ValueSet/valueset-dxtc-example"/>
    </relatedArtifact>
    <relatedArtifact>
        <type value="composed-of"/>
      <resource value="http://hl7.org/fhir/us/ecr/ValueSet/valueset-ostc-example"/>
    </relatedArtifact>
    <relatedArtifact>
        <type value="composed-of"/>
      <resource value="http://hl7.org/fhir/us/ecr/ValueSet/valueset-lotc-example"/>
    </relatedArtifact>
    <relatedArtifact>
        <type value="composed-of"/>
      <resource value="http://hl7.org/fhir/us/ecr/ValueSet/valueset-lrtc-example"/>
    </relatedArtifact>
    <relatedArtifact>
        <type value="composed-of"/>
      <resource value="http://hl7.org/fhir/us/ecr/ValueSet/valueset-mrtc-example"/>
    </relatedArtifact>
    <relatedArtifact>
        <type value="composed-of"/>
      <resource value="http://hl7.org/fhir/us/ecr/ValueSet/valueset-iztc-example"/>
    </relatedArtifact>
</Library>